lad_common/__init__.py
lad_common/db.py
lad_common/models/__init__.py
lad_common/utils/__init__.py
lad_common-0.27.0.dist-info/METADATA
lad_common-0.27.0.dist-info/WHEEL
lad_common-0.27.0.dist-info/top_level.txt
lad_common-0.27.0.dist-info/RECORD
