Metadata-Version: 2.1
Name: lad-common
Version: 0.27.0
Summary: A package with common functionality used in lad platform
Home-page: https://github.com/amdrey-maralin/lad
Author: Andrey Maralin
Author-email: a.a.maralin@gmail.com
License: UNKNOWN
Platform: UNKNOWN
Classifier: Programming Language :: Python :: 3
Classifier: License :: OSI Approved :: MIT License
Classifier: Operating System :: OS Independent
Requires-Python: >=3.6
